{
  "name": "Day 2 Automation",
  "nodes": [
    {
      "parameters": {
        "rule": {
          "interval": [
            {
              "triggerAtHour": 9
            }
          ]
        }
      },
      "type": "n8n-nodes-base.scheduleTrigger",
      "typeVersion": 1.3,
      "position": [
        -256,
        -32
      ],
      "id": "be911165-0f26-4a27-9da6-800dc1d5ced4",
      "name": "Schedule Trigger"
    },
    {
      "parameters": {
        "documentId": {
          "__rl": true,
          "value": "1rW3TCKv2YucLqHl17q3eNKjThWCbxCHqIMHwOAfJI24",
          "mode": "list",
          "cachedResultName": "RetailCo Sales Results",
          "cachedResultUrl": "https://docs.google.com/spreadsheets/d/1rW3TCKv2YucLqHl17q3eNKjThWCbxCHqIMHwOAfJI24/edit?usp=drivesdk"
        },
        "sheetName": {
          "__rl": true,
          "value": 454810268,
          "mode": "list",
          "cachedResultName": "Results",
          "cachedResultUrl": "https://docs.google.com/spreadsheets/d/1rW3TCKv2YucLqHl17q3eNKjThWCbxCHqIMHwOAfJI24/edit#gid=454810268"
        },
        "options": {}
      },
      "type": "n8n-nodes-base.googleSheets",
      "typeVersion": 4.7,
      "position": [
        -48,
        -32
      ],
      "id": "899770f5-4a92-402e-a2b1-4a6b10cd7344",
      "name": "Get row(s) in sheet",
      "credentials": {
        "googleSheetsOAuth2Api": {
          "id": "Ed1Bmw5Yyp4LT2G8",
          "name": "Google Sheets OAuth2 API"
        }
      }
    },
    {
      "parameters": {
        "conditions": {
          "options": {
            "caseSensitive": true,
            "leftValue": "",
            "typeValidation": "strict",
            "version": 3
          },
          "conditions": [
            {
              "id": "18884419-d651-45ad-85f7-5ae257d9a3f8",
              "leftValue": "={{ $json.risk_level }}",
              "rightValue": "high",
              "operator": {
                "type": "string",
                "operation": "equals",
                "name": "filter.operator.equals"
              }
            },
            {
              "id": "6d40dde6-8260-4915-95d9-daf250cf0daf",
              "leftValue": "={{ $json.date }}",
              "rightValue": "={{ $now.format('yyyy-MM-dd') }}",
              "operator": {
                "type": "string",
                "operation": "equals",
                "name": "filter.operator.equals"
              }
            }
          ],
          "combinator": "and"
        },
        "options": {}
      },
      "type": "n8n-nodes-base.if",
      "typeVersion": 2.3,
      "position": [
        160,
        -32
      ],
      "id": "fabd03bb-2fe2-4567-81eb-cd016f495ff9",
      "name": "If"
    },
    {
      "parameters": {
        "authentication": "oAuth2",
        "select": "channel",
        "channelId": {
          "__rl": true,
          "value": "C0B8RHAPTT8",
          "mode": "list",
          "cachedResultName": "sales-alerts"
        },
        "text": "=🔴 *High-risk customer alert*  *Customer:* {{ $json.customer_id }} *Category:* {{ $json.top_category }} *Last purchase:* {{ $json.days_since_last }} days ago *Why at risk:* {{ $json.reason }}  *Suggested message to send:* {{ $json.outreach_message }}",
        "otherOptions": {}
      },
      "type": "n8n-nodes-base.slack",
      "typeVersion": 2.5,
      "position": [
        352,
        -16
      ],
      "id": "d3a10789-34f7-42e1-94a5-acbe9055ca22",
      "name": "Send a message",
      "webhookId": "2c37d164-ff09-4234-bafe-b60142cd6fb8",
      "credentials": {
        "slackOAuth2Api": {
          "id": "BKCYZEoPrgFP9QxF",
          "name": "Slack OAuth2 API"
        }
      }
    },
    {
      "parameters": {
        "operation": "append",
        "documentId": {
          "__rl": true,
          "value": "1rW3TCKv2YucLqHl17q3eNKjThWCbxCHqIMHwOAfJI24",
          "mode": "list",
          "cachedResultName": "RetailCo Sales Results",
          "cachedResultUrl": "https://docs.google.com/spreadsheets/d/1rW3TCKv2YucLqHl17q3eNKjThWCbxCHqIMHwOAfJI24/edit?usp=drivesdk"
        },
        "sheetName": {
          "__rl": true,
          "value": 454810268,
          "mode": "list",
          "cachedResultName": "Results",
          "cachedResultUrl": "https://docs.google.com/spreadsheets/d/1rW3TCKv2YucLqHl17q3eNKjThWCbxCHqIMHwOAfJI24/edit#gid=454810268"
        },
        "columns": {
          "mappingMode": "defineBelow",
          "value": {
            "date": "={{ $json.date }}",
            "customer_id": "={{ $json.customer_id }}",
            "purchase_count_90d": "={{ $json.purchase_count_90d }}",
            "days_since_last": "={{ $json.days_since_last }}",
            "reason": "={{ $json.reason }}",
            "outreach_message": "={{ $json.outreach_message }}",
            "top_category": "={{ $json.top_category }}",
            "avg_order_value": "={{ $json.avg_order_value }}",
            "risk_level": "={{ $json.risk_level }}"
          },
          "matchingColumns": [],
          "schema": [
            {
              "id": "date",
              "displayName": "date",
              "required": false,
              "defaultMatch": false,
              "display": true,
              "type": "string",
              "canBeUsedToMatch": true
            },
            {
              "id": "customer_id",
              "displayName": "customer_id",
              "required": false,
              "defaultMatch": false,
              "display": true,
              "type": "string",
              "canBeUsedToMatch": true
            },
            {
              "id": "purchase_count_90d",
              "displayName": "purchase_count_90d",
              "required": false,
              "defaultMatch": false,
              "display": true,
              "type": "string",
              "canBeUsedToMatch": true
            },
            {
              "id": "days_since_last",
              "displayName": "days_since_last",
              "required": false,
              "defaultMatch": false,
              "display": true,
              "type": "string",
              "canBeUsedToMatch": true
            },
            {
              "id": "avg_order_value",
              "displayName": "avg_order_value",
              "required": false,
              "defaultMatch": false,
              "display": true,
              "type": "string",
              "canBeUsedToMatch": true
            },
            {
              "id": "top_category",
              "displayName": "top_category",
              "required": false,
              "defaultMatch": false,
              "display": true,
              "type": "string",
              "canBeUsedToMatch": true
            },
            {
              "id": "risk_level",
              "displayName": "risk_level",
              "required": false,
              "defaultMatch": false,
              "display": true,
              "type": "string",
              "canBeUsedToMatch": true
            },
            {
              "id": "reason",
              "displayName": "reason",
              "required": false,
              "defaultMatch": false,
              "display": true,
              "type": "string",
              "canBeUsedToMatch": true
            },
            {
              "id": "outreach_message",
              "displayName": "outreach_message",
              "required": false,
              "defaultMatch": false,
              "display": true,
              "type": "string",
              "canBeUsedToMatch": true
            }
          ],
          "attemptToConvertTypes": false,
          "convertFieldsToString": false
        },
        "options": {}
      },
      "type": "n8n-nodes-base.googleSheets",
      "typeVersion": 4.7,
      "position": [
        352,
        160
      ],
      "id": "60da4cd8-3d9e-4783-99fd-e4f891109c63",
      "name": "Append row in sheet",
      "credentials": {
        "googleSheetsOAuth2Api": {
          "id": "Ed1Bmw5Yyp4LT2G8",
          "name": "Google Sheets OAuth2 API"
        }
      }
    },
    {
      "parameters": {
        "sendTo": "={{ $json.customer_email }}",
        "subject": "We miss you — a special offer inside",
        "emailType": "text",
        "message": "={{ $json.outreach_message }}",
        "options": {}
      },
      "type": "n8n-nodes-base.gmail",
      "typeVersion": 2.2,
      "position": [
        336,
        -208
      ],
      "id": "83571585-5350-41b0-929b-991accf01174",
      "name": "Send a message1",
      "webhookId": "0b228de6-6aaa-4b92-9861-7674b28d83de",
      "credentials": {
        "gmailOAuth2": {
          "id": "v3Wd4ZqYBj0tdZNh",
          "name": "Gmail OAuth2 API"
        }
      }
    },
    {
      "parameters": {
        "from": "+14155238886",
        "to": "=whatsapp:{{ $json.customer_phone }}",
        "message": "={{ $json.outreach_message }}",
        "options": {}
      },
      "type": "n8n-nodes-base.twilio",
      "typeVersion": 1,
      "position": [
        336,
        -336
      ],
      "id": "2366e381-8a2e-4bc3-a27d-346ac69c95be",
      "name": "Send an SMS/MMS/WhatsApp message"
    }
  ],
  "pinData": {},
  "connections": {
    "Schedule Trigger": {
      "main": [
        [
          {
            "node": "Get row(s) in sheet",
            "type": "main",
            "index": 0
          }
        ]
      ]
    },
    "Get row(s) in sheet": {
      "main": [
        [
          {
            "node": "If",
            "type": "main",
            "index": 0
          }
        ]
      ]
    },
    "If": {
      "main": [
        [
          {
            "node": "Send a message1",
            "type": "main",
            "index": 0
          },
          {
            "node": "Send a message",
            "type": "main",
            "index": 0
          },
          {
            "node": "Send an SMS/MMS/WhatsApp message",
            "type": "main",
            "index": 0
          }
        ],
        [
          {
            "node": "Append row in sheet",
            "type": "main",
            "index": 0
          }
        ]
      ]
    },
    "Send a message": {
      "main": [
        []
      ]
    },
    "Send a message1": {
      "main": [
        []
      ]
    }
  },
  "active": false,
  "settings": {
    "executionOrder": "v1",
    "binaryMode": "separate"
  },
  "versionId": "92e56540-5e48-4f9f-9d60-4bc6a6633b13",
  "meta": {
    "templateCredsSetupCompleted": true,
    "instanceId": "bdeb7358cbb3f1926c6ed9ea014321ff87bd3a1d49cc0fddd336a9ea0e73739e"
  },
  "nodeGroups": [],
  "id": "g95on0xVqLS73HU0",
  "tags": []
}